EMaligner
root
