Metadata-Version: 1.0
Name: EMaligner
Version: 1.0.2
Summary: global alignment of features between images
Home-page: https://github.com/AllenInstitute/EM_Aligner_python
Author: Daniel Kapner
Author-email: danielk@alleninstitute.org
License: UNKNOWN
Platform: UNKNOWN
